setup.py
firstPackToPypI/Binomialdistribution.py
firstPackToPypI/Gaussiandistribution.py
firstPackToPypI/Generaldistribution.py
firstPackToPypI/__init__.py
firstPackToPypI.egg-info/PKG-INFO
firstPackToPypI.egg-info/SOURCES.txt
firstPackToPypI.egg-info/dependency_links.txt
firstPackToPypI.egg-info/not-zip-safe
firstPackToPypI.egg-info/top_level.txt