Metadata-Version: 1.0
Name: firstPackToPypI
Version: 0.1
Summary: Gaussian distributions
Home-page: UNKNOWN
Author: Anas Abuelhaag
Author-email: anaselhaag@gmail.com
License: UNKNOWN
Platform: UNKNOWN
